[
  {
    "quest": "wohnen",
    "answer": [
      "жить",
      "я живу",
      "ты живёшь",
      "он / она / оно живёт",
      "мы живём",
      "вы живёте",
      "они живут"
    ]
  },
  {
    "quest": "sprechen",
    "answer": [
      "говорить",
      "я говорю",
      "ты говоришь",
      "он / она / оно говорит",
      "мы говорим",
      "вы говорите",
      "они говорят"
    ]
  },
  {
    "quest": "arbeiten",
    "answer": [
      "работать",
      "я работаю",
      "ты работаешь",
      "он / она / оно работает",
      "мы работаем",
      "вы работаете",
      "они работают"
    ]
  },
  {
    "quest": [
      "wissen",
      "kennen"
    ],
    "answer": [
      "знать",
      "я знаю",
      "ты знаешь",
      "он / она / оно знает",
      "мы знаем",
      "вы знаете",
      "они знают"
    ]
  },
  {
    "quest": [
      "machen",
      "tun"
    ],
    "answer": [
      "делать",
      "я делаю",
      "ты делаешь",
      "он / она / оно делает",
      "мы делаем",
      "вы делаете",
      "они делают"
    ]
  }
]